Adafruit_MCP3008/__init__.py
Adafruit_MCP3008/MCP3008.py
Adafruit_MCP3008-1.0.2.dist-info/metadata.json
Adafruit_MCP3008-1.0.2.dist-info/METADATA
Adafruit_MCP3008-1.0.2.dist-info/RECORD
Adafruit_MCP3008-1.0.2.dist-info/WHEEL
Adafruit_MCP3008-1.0.2.dist-info/DESCRIPTION.rst
Adafruit_MCP3008-1.0.2.dist-info/dependency_links.txt
Adafruit_MCP3008-1.0.2.dist-info/top_level.txt
