Metadata-Version: 1.1
Name: Adafruit_MCP3008
Version: 1.0.2
Summary: Python code to use the MCP3008 analog to digital converter with a Raspberry Pi or BeagleBone black.
Home-page: https://github.com/adafruit/Adafruit_Python_MCP3008/
Author: Tony DiCola
Author-email: tdicola@adafruit.com
License: MIT
Platform: UNKNOWN
Classifier: Development Status :: 4 - Beta
Classifier: Operating System :: POSIX :: Linux
Classifier: License :: OSI Approved :: MIT License
Classifier: Intended Audience :: Developers
Classifier: Programming Language :: Python :: 2.7
Classifier: Programming Language :: Python :: 3
Classifier: Topic :: Software Development
Classifier: Topic :: System :: Hardware
